orval/__init__.py
orval/arrays.py
orval/byte_utils.py
orval/datetimes.py
orval/hashing.py
orval/py.typed
orval/strings.py
orval/utils.py
orval-0.0.8.dist-info/LICENSE
orval-0.0.8.dist-info/METADATA
orval-0.0.8.dist-info/WHEEL
orval-0.0.8.dist-info/RECORD
