Metadata-Version: 2.1
Name: orval
Version: 0.0.8
Summary: A Python package containing a small set of utility functions not found in Python's standard library. It is lightweight, written in pure Python, and has no dependencies.
Home-page: https://github.com/lukin0110/orval/
License: MIT
Author: Maarten Huijsmans
Author-email: maarten@lukin.be
Requires-Python: >=3.10.0,<4.0
Classifier: Development Status :: 3 - Alpha
Classifier: Intended Audience :: Developers
Classifier: Intended Audience :: Information Technology
Classifier: License :: OSI Approved :: MIT License
Classifier: Operating System :: OS Independent
Classifier: Programming Language :: Python :: 3
Classifier: Programming Language :: Python :: 3.10
Classifier: Programming Language :: Python :: 3.11
Classifier: Programming Language :: Python :: 3.12
Classifier: Programming Language :: Python :: 3.13
Classifier: Programming Language :: Python :: 3 :: Only
Classifier: Topic :: Internet
Classifier: Topic :: Software Development :: Libraries :: Python Modules
Classifier: Topic :: Utilities
Classifier: Typing :: Typed
Project-URL: Repository, https://github.com/lukin0110/orval/
